tclab_cae/__init__.py
tclab_cae/__main__.py
tclab_cae/experiment.py
tclab_cae/gui.py
tclab_cae/historian.py
tclab_cae/labtime.py
tclab_cae/tclab_cae.py
tclab_cae/version.py
tclab_cae-0.5.3.dist-info/METADATA
tclab_cae-0.5.3.dist-info/WHEEL
tclab_cae-0.5.3.dist-info/top_level.txt
tclab_cae-0.5.3.dist-info/RECORD
