Metadata-Version: 2.1
Name: tclab-cae
Version: 0.5.3
Summary: Python bindings for the BYU Arduino Temperature Control Lab and extended by Control Automatico Educación
Home-page: https://github.com/sergioacg/TCLAB_PYTHON_CAE/tree/master
Keywords: apmonitor control hardware,Control Automatico Educacion,tclab_cae
Classifier: Development Status :: 3 - Alpha
Classifier: Intended Audience :: Education
Classifier: Topic :: System :: Hardware :: Hardware Drivers
Classifier: License :: OSI Approved :: Apache Software License
Classifier: Programming Language :: Python :: 2
Classifier: Programming Language :: Python :: 2.7
Classifier: Programming Language :: Python :: 3
Classifier: Programming Language :: Python :: 3.4
Classifier: Programming Language :: Python :: 3.5
Classifier: Programming Language :: Python :: 3.6
Requires-Dist: pyserial
Provides-Extra: dev
Requires-Dist: check-manifest ; extra == 'dev'
Provides-Extra: test
Requires-Dist: coverage ; extra == 'test'
Requires-Dist: pytest ; extra == 'test'
